commonroad_route_planner/__init__.py
commonroad_route_planner/fast_api/__init__.py
commonroad_route_planner/fast_api/fast_api.py
commonroad_route_planner/frenet_tools/__init__.py
commonroad_route_planner/frenet_tools/route_extendor.py
commonroad_route_planner/frenet_tools/route_slice.py
commonroad_route_planner/lane_changing/__init__.py
commonroad_route_planner/lane_changing/change_instruction.py
commonroad_route_planner/lane_changing/change_position.py
commonroad_route_planner/lane_changing/lane_change_handler.py
commonroad_route_planner/lane_changing/lane_change_methods/__init__.py
commonroad_route_planner/lane_changing/lane_change_methods/method_interface.py
commonroad_route_planner/lane_changing/lane_change_methods/polynomial_change.py
commonroad_route_planner/lanelet_sequence.py
commonroad_route_planner/map_matching.py
commonroad_route_planner/planners/__init__.py
commonroad_route_planner/planners/base_route_planner.py
commonroad_route_planner/planners/networkx.py
commonroad_route_planner/planners/no_goal_found_planner.py
commonroad_route_planner/reference_path.py
commonroad_route_planner/reference_path_planner.py
commonroad_route_planner/route_generation_strategies/__init__.py
commonroad_route_planner/route_generation_strategies/base_generation_strategy.py
commonroad_route_planner/route_generation_strategies/default_generation_strategy.py
commonroad_route_planner/route_planner.py
commonroad_route_planner/route_sections/__init__.py
commonroad_route_planner/route_sections/lanelet_section.py
commonroad_route_planner/utility/__init__.py
commonroad_route_planner/utility/exceptions.py
commonroad_route_planner/utility/overtake_init_state.py
commonroad_route_planner/utility/polyline_operations/__init__.py
commonroad_route_planner/utility/polyline_operations/polyline_operations.py
commonroad_route_planner/utility/route_util.py
commonroad_route_planner/utility/visualization.py
commonroad_route_planner-2025.1.0.dist-info/LICENSE.txt
commonroad_route_planner-2025.1.0.dist-info/METADATA
commonroad_route_planner-2025.1.0.dist-info/WHEEL
commonroad_route_planner-2025.1.0.dist-info/RECORD
