Metadata-Version: 2.3
Name: commonroad-route-planner
Version: 2025.1.0
Summary: Route and reference path planning tool for CommonRoad scenarios
License: BSD
Keywords: autonomous,automated,vehicles,driving,motion,planning,prediction
Author: Tobias Mascetta
Author-email: <commonroad@lists.lrz.de>
Requires-Python: >=3.9, <3.12
Classifier: Programming Language :: Python :: 3.9
Classifier: License :: OSI Approved :: BSD License
Classifier: Operating System :: POSIX :: Linux
Requires-Dist: commonroad-clcs (>=2025.1.0,<2026.0.0)
Requires-Dist: commonroad-io (>=2022.2)
Requires-Dist: matplotlib (>=3.1.2)
Requires-Dist: networkx (>=2.4)
Requires-Dist: numpy (>=1.17.4)
Requires-Dist: shapely (>=1.6.4.post2)
